sparql_slurper/__init__.py
sparql_slurper/_graphdb_slurpygraph.py
sparql_slurper/_slurpygraph.py
sparql_slurper-0.3.4.dist-info/AUTHORS
sparql_slurper-0.3.4.dist-info/METADATA
sparql_slurper-0.3.4.dist-info/WHEEL
sparql_slurper-0.3.4.dist-info/pbr.json
sparql_slurper-0.3.4.dist-info/top_level.txt
sparql_slurper-0.3.4.dist-info/RECORD
