Metadata-Version: 1.2
Name: sparql-slurper
Version: 0.3.4
Summary: SPARQL Slurper for rdflib
Home-page: http://github.com/hsolbrig/sparql_slurper
Author: Harold Solbrig
Author-email: solbrig@jhu.edu
License: Apache 2.0
Keywords: SPARQL,ShEx,RDF,rdflib
Platform: UNKNOWN
Requires-Python: >=3.6
